<?xml version = '1.0' encoding = 'UTF-8'?>
<FKIndexAssociation class="oracle.dbtools.crest.model.design.relational.FKIndexAssociation" directorySegmentName="seg_1" id="3BFED51E-2E5B-3487-FD13-805672B198B0" containerWithKeyObject="20A872BA-46C8-8B51-00B9-831914F78D28" localFKIndex="01E4ED3A-4CE2-2F14-9BD0-3FCAA5167528" name="Linked_enterprise_Party_FK">
<createdBy>ostarij</createdBy>
<createdTime>2021-11-10 11:49:41 UTC</createdTime>
<commentInRDBMS><![CDATA[has]]></commentInRDBMS>
<generatorID>F93FDDA3-4D15-6674-2AD8-2A544395AD8D</generatorID>
<ownerDesignName>BIRD data models</ownerDesignName>
<referredTableLongName>Party</referredTableLongName>
<deleteRule>NO ACTION</deleteRule>
<referredTableID>2447AC50-2ABA-B6AF-24F7-565FFE8035A2</referredTableID>
<keyObject>AAB5BF71-9938-9075-A54D-68BD7DEDA36B</keyObject>
<referredKeyID>AAB5BF71-9938-9075-A54D-68BD7DEDA36B</referredKeyID>
<mandatory>true</mandatory>
<refColNames>Party_identifier</refColNames>
<transferable>true</transferable>
<rely>false</rely>
<columnDependencyConstraintGenerateInDDL>true</columnDependencyConstraintGenerateInDDL>
</FKIndexAssociation>
