<?xml version = '1.0' encoding = 'UTF-8'?>
<Entity class="oracle.dbtools.crest.model.design.logical.Entity" directorySegmentName="seg_5" id="8D276167-45CA-B564-B28C-7849EB0D5ADC" name="Security position hedged by Over the counter (OTC) derivative">
<createdBy>lindomi</createdBy>
<createdTime>2021-10-27 07:49:02 UTC</createdTime>
<commentInRDBMS><![CDATA[A Security position hedged by Over the counter (OTC) derivative is the combination of a Security position and an Over the counter (OTC) derivative as a hedge that indicates which (portion of a) Security position is hedged by which Over the counter (OTC) derivative (acting in the role of an Over the counter (OTC) derivative as a hedge).]]></commentInRDBMS>
<ownerDesignName>BIRD data models</ownerDesignName>
<shouldEngineer>false</shouldEngineer>
<engineerTo>
<item key="AEFDAE93-361A-74FC-D9B0-896822C5F2BB" value="false"/>
<item key="9F71AC75-C64B-3A4F-AE9B-7E0028CEC114" value="false"/>
<item key="24FC9E45-18D3-C550-6BAD-4693BE2883E4" value="false"/>
<item key="6BCEF519-13E1-B08A-2794-C031B6E1ADA6" value="false"/>
</engineerTo>
<typeID>E3679F77-0ED6-93EB-F366-44CA2F802395</typeID>
<adequatelyNormalized>NO</adequatelyNormalized>
<expectedVolumes>0</expectedVolumes>
<fwdEngineeringStrategyName>Single Table</fwdEngineeringStrategyName>
<growthPercent>0</growthPercent>
<growthType>Year</growthType>
<maxVolumes>9999999</maxVolumes>
<minVolumes>0</minVolumes>
<normalForm>Third</normalForm>
<preferredAbbreviation>SCRTY_PSTN_HDGD_OTC_DRVTV</preferredAbbreviation>
<attributes itemClass="oracle.dbtools.crest.model.design.logical.Attribute">
<Attribute name="Over the counter (OTC) Derivative Instrument identifier" id="04312425-EEE1-8C8F-5169-F1A52229DBB0">
<createdBy>lindomi</createdBy>
<createdTime>2021-10-27 07:50:48 UTC</createdTime>
<comment><![CDATA[The instrument identifier of the invovled over the counter derivative.]]></comment>
<generatorID>C4E13389-745E-83AC-904E-42B3FF543CB6</generatorID>
<ownerDesignName>BIRD data models</ownerDesignName>
<engineerTo>
<item key="AEFDAE93-361A-74FC-D9B0-896822C5F2BB" value="true"/>
<item key="9F71AC75-C64B-3A4F-AE9B-7E0028CEC114" value="true"/>
<item key="24FC9E45-18D3-C550-6BAD-4693BE2883E4" value="true"/>
<item key="6BCEF519-13E1-B08A-2794-C031B6E1ADA6" value="true"/>
</engineerTo>
<referedAttribute>B9DD5C72-06D0-68F2-7638-4D9E9CC3F2D5</referedAttribute>
<use>0</use>
<logicalDatatype>A3A3C77D-0366-9768-FF89-1C25E56881C8</logicalDatatype>
<domain>bedac99c-65df-4709-835b-fbf0381d048e</domain>
<ownDataTypeParameters>,,</ownDataTypeParameters>
<preferredAbbreviation>OTC_DRVTV_INSTRMNT_ID</preferredAbbreviation>
</Attribute>
<Attribute name="Over the counter (OTC) derivative role type" id="359DF663-B903-96E6-A555-D48A45A77062">
<createdBy>lindomi</createdBy>
<createdTime>2021-10-27 07:50:48 UTC</createdTime>
<comment><![CDATA[The over the counter derivative role.]]></comment>
<generatorID>C4E13389-745E-83AC-904E-42B3FF543CB6</generatorID>
<ownerDesignName>BIRD data models</ownerDesignName>
<engineerTo>
<item key="AEFDAE93-361A-74FC-D9B0-896822C5F2BB" value="true"/>
<item key="9F71AC75-C64B-3A4F-AE9B-7E0028CEC114" value="true"/>
<item key="24FC9E45-18D3-C550-6BAD-4693BE2883E4" value="true"/>
<item key="6BCEF519-13E1-B08A-2794-C031B6E1ADA6" value="true"/>
</engineerTo>
<referedAttribute>D7D97A09-E812-C1EF-FDEA-7141A39D65E6</referedAttribute>
<use>0</use>
<logicalDatatype>A3A3C77D-0366-9768-FF89-1C25E56881C8</logicalDatatype>
<domain>349AC89A-5AAB-E070-84D0-FA8227AC4745</domain>
<ownDataTypeParameters>,,</ownDataTypeParameters>
<preferredAbbreviation>OTC_DRVTV_RL_TYP</preferredAbbreviation>
</Attribute>
<Attribute name="Security identifier" id="B38BF1A7-0828-E8E0-3843-A9ED503A1F19">
<createdBy>lindomi</createdBy>
<createdTime>2021-10-27 07:55:34 UTC</createdTime>
<comment><![CDATA[An identifier to uniquely identify each security.]]></comment>
<generatorID>CB3664A0-6595-8A1D-F50C-47122EB584EA</generatorID>
<ownerDesignName>BIRD data models</ownerDesignName>
<engineerTo>
<item key="AEFDAE93-361A-74FC-D9B0-896822C5F2BB" value="true"/>
<item key="9F71AC75-C64B-3A4F-AE9B-7E0028CEC114" value="true"/>
<item key="24FC9E45-18D3-C550-6BAD-4693BE2883E4" value="true"/>
<item key="6BCEF519-13E1-B08A-2794-C031B6E1ADA6" value="true"/>
</engineerTo>
<referedAttribute>A73E5CAA-6B35-CDB1-BE0A-FD118888C056</referedAttribute>
<use>0</use>
<logicalDatatype>A3A3C77D-0366-9768-FF89-1C25E56881C8</logicalDatatype>
<domain>12DFCE00-085A-4E8C-BE55-52350D849DA7</domain>
<ownDataTypeParameters>,,</ownDataTypeParameters>
<preferredAbbreviation>SCRTY_ID</preferredAbbreviation>
</Attribute>
<Attribute name="Investor Party role type" id="368548CE-68D2-AD6A-0DC1-ED2E6F090ABE">
<createdBy>lindomi</createdBy>
<createdTime>2021-10-27 07:55:34 UTC</createdTime>
<comment><![CDATA[The investor role.]]></comment>
<generatorID>CB3664A0-6595-8A1D-F50C-47122EB584EA</generatorID>
<ownerDesignName>BIRD data models</ownerDesignName>
<engineerTo>
<item key="AEFDAE93-361A-74FC-D9B0-896822C5F2BB" value="true"/>
<item key="9F71AC75-C64B-3A4F-AE9B-7E0028CEC114" value="true"/>
<item key="24FC9E45-18D3-C550-6BAD-4693BE2883E4" value="true"/>
<item key="6BCEF519-13E1-B08A-2794-C031B6E1ADA6" value="true"/>
</engineerTo>
<referedAttribute>C8E9B405-C94F-6E8F-5DBE-464CB85C76BD</referedAttribute>
<use>0</use>
<logicalDatatype>A3A3C77D-0366-9768-FF89-1C25E56881C8</logicalDatatype>
<domain>D0551245-E927-3180-FE42-C9D973931F73</domain>
<ownDataTypeParameters>,,</ownDataTypeParameters>
<preferredAbbreviation>INVSTR_PRTY_RL_TYP</preferredAbbreviation>
</Attribute>
<Attribute name="Investor Party identifier" id="EB3A73B9-B144-5CAC-628D-BD101C05359B">
<createdBy>lindomi</createdBy>
<createdTime>2021-10-27 07:55:34 UTC</createdTime>
<comment><![CDATA[The party identifier of the involved investor.]]></comment>
<generatorID>CB3664A0-6595-8A1D-F50C-47122EB584EA</generatorID>
<ownerDesignName>BIRD data models</ownerDesignName>
<engineerTo>
<item key="AEFDAE93-361A-74FC-D9B0-896822C5F2BB" value="true"/>
<item key="9F71AC75-C64B-3A4F-AE9B-7E0028CEC114" value="true"/>
<item key="24FC9E45-18D3-C550-6BAD-4693BE2883E4" value="true"/>
<item key="6BCEF519-13E1-B08A-2794-C031B6E1ADA6" value="true"/>
</engineerTo>
<referedAttribute>437168AE-6239-C93C-4403-089A9B1A446C</referedAttribute>
<use>0</use>
<logicalDatatype>A3A3C77D-0366-9768-FF89-1C25E56881C8</logicalDatatype>
<domain>bedac99c-65df-4709-835b-fbf0381d048e</domain>
<ownDataTypeParameters>,,</ownDataTypeParameters>
<preferredAbbreviation>INVSTR_PRTY_ID</preferredAbbreviation>
</Attribute>
<Attribute name="Prudential portfolio type" id="EFDF215F-A607-4919-2119-6D492194C2EA">
<createdBy>lindomi</createdBy>
<createdTime>2021-10-27 07:55:34 UTC</createdTime>
<comment><![CDATA[A discriminator to distinguish between trading and banking (or non-trading) book.]]></comment>
<generatorID>CB3664A0-6595-8A1D-F50C-47122EB584EA</generatorID>
<ownerDesignName>BIRD data models</ownerDesignName>
<engineerTo>
<item key="AEFDAE93-361A-74FC-D9B0-896822C5F2BB" value="true"/>
<item key="9F71AC75-C64B-3A4F-AE9B-7E0028CEC114" value="true"/>
<item key="24FC9E45-18D3-C550-6BAD-4693BE2883E4" value="true"/>
<item key="6BCEF519-13E1-B08A-2794-C031B6E1ADA6" value="true"/>
</engineerTo>
<referedAttribute>DC215B99-E32E-45DB-0F3D-F08FFEAD753B</referedAttribute>
<use>0</use>
<logicalDatatype>A3A3C77D-0366-9768-FF89-1C25E56881C8</logicalDatatype>
<domain>9ECA7EA5-B456-4AD8-AA91-4AD16E2D4AD7</domain>
<ownDataTypeParameters>,,</ownDataTypeParameters>
<preferredAbbreviation>PRDNTL_PRFL_TYP</preferredAbbreviation>
</Attribute>
</attributes>
<identifiers itemClass="oracle.dbtools.crest.model.design.logical.CandidateKey">
<identifier id="699A5CA4-85B3-6B70-CF5B-90253C19F1B9" name="Security position hedged by Over the counter (OTC) derivative PK">
<createdBy>lindomi</createdBy>
<createdTime>2021-10-27 07:50:48 UTC</createdTime>
<ownerDesignName>BIRD data models</ownerDesignName>
<engineerTo>
<item key="AEFDAE93-361A-74FC-D9B0-896822C5F2BB" value="true"/>
<item key="9F71AC75-C64B-3A4F-AE9B-7E0028CEC114" value="true"/>
<item key="24FC9E45-18D3-C550-6BAD-4693BE2883E4" value="true"/>
<item key="6BCEF519-13E1-B08A-2794-C031B6E1ADA6" value="true"/>
</engineerTo>
<pk>true</pk>
<usedAttributes>
<attributeRef>04312425-EEE1-8C8F-5169-F1A52229DBB0</attributeRef>
<attributeRef>359DF663-B903-96E6-A555-D48A45A77062</attributeRef>
<attributeRef>B38BF1A7-0828-E8E0-3843-A9ED503A1F19</attributeRef>
<attributeRef>368548CE-68D2-AD6A-0DC1-ED2E6F090ABE</attributeRef>
<attributeRef>EB3A73B9-B144-5CAC-628D-BD101C05359B</attributeRef>
<attributeRef>EFDF215F-A607-4919-2119-6D492194C2EA</attributeRef>
</usedAttributes>
</identifier>
</identifiers>
</Entity>
