<?xml version = '1.0' encoding = 'UTF-8'?>
<Relation class="oracle.dbtools.crest.model.design.logical.Relation" name="Renegotiated financial asset instrument with forbearance measure has Renegotiated financial asset instrument with forbearance measure derived data" directorySegmentName="seg_5" id="1B86742D-6BA5-97B6-D891-3224F9FF53E1">
<createdBy>bosarie</createdBy>
<createdTime>2023-11-02 14:43:04 UTC</createdTime>
<ownerDesignName>BIRD data models</ownerDesignName>
<engineerTo>
<item key="C083FD85-D1B9-E583-74F8-D21AEF72E2BC" value="true"/>
<item key="2F95CE3A-CB8C-BD28-A553-EDBE7F94003D" value="true"/>
<item key="5CF11FB1-F95F-60BC-DA98-ABFECEE7315A" value="true"/>
<item key="D692C862-C9D4-A57D-98F6-C0D7D8DBCCCF" value="true"/>
</engineerTo>
<sourcePk>791B8411-7E00-08FE-C4F8-E18BAA32B7B7</sourcePk>
<dominantRole>8C62256E-C754-34FA-25DD-E5EA41B6F74E</dominantRole>
<identifying>true</identifying>
<optionalSource>true</optionalSource>
<optionalTarget>false</optionalTarget>
<sourceCardinality>1</sourceCardinality>
<sourceEntity>8C62256E-C754-34FA-25DD-E5EA41B6F74E</sourceEntity>
<targetCardinalityString>1</targetCardinalityString>
<targetEntity>048D458D-00B0-1F3C-D9A5-87EAE9C831CA</targetEntity>
<transferable>true</transferable>
<deleteRule>NO ACTION</deleteRule>
</Relation>
