<?xml version = '1.0' encoding = 'UTF-8'?>
<FKIndexAssociation class="oracle.dbtools.crest.model.design.relational.FKIndexAssociation" directorySegmentName="seg_0" id="AA02D28B-69AD-73EC-3E55-AEC64FB1AF95" containerWithKeyObject="8EA99692-19C6-DA78-A598-105FA48927FA" localFKIndex="B6741948-BDE9-2303-A3CA-5A16426B86F5" name="ASST_PL_LN_ASSGNMNT_ASST_PL_FK">
<createdBy>nuvolia</createdBy>
<createdTime>2024-04-10 12:45:06 UTC</createdTime>
<commentInRDBMS><![CDATA[comprises]]></commentInRDBMS>
<generatorID>FDB5C2E5-36D2-CBB7-331F-9DF4A14D0521</generatorID>
<ownerDesignName>BIRD data models</ownerDesignName>
<referredTableLongName>ASST_PL</referredTableLongName>
<deleteRule>NO ACTION</deleteRule>
<referredTableID>561F142B-6F21-EDFD-A35C-ED3725BF56F9</referredTableID>
<keyObject>DEA98F39-F39A-0B52-25D9-212AD925535F</keyObject>
<referredKeyID>DEA98F39-F39A-0B52-25D9-212AD925535F</referredKeyID>
<mandatory>true</mandatory>
<refColNames>ASST_PL_ID,ASST_PL_RFRNC_DT,ASST_PL_RPRTNG_AGNT_ID</refColNames>
<transferable>true</transferable>
<rely>false</rely>
<columnDependencyConstraintGenerateInDDL>true</columnDependencyConstraintGenerateInDDL>
</FKIndexAssociation>
