<?xml version = '1.0' encoding = 'UTF-8'?>
<Entity class="oracle.dbtools.crest.model.design.logical.Entity" directorySegmentName="seg_7" id="7E6B5895-2EAE-724A-CF8B-C9875CD17314" name="Fair value designation">
<createdBy>ostarij</createdBy>
<createdTime>2022-07-28 15:53:06 UTC</createdTime>
<commentInRDBMS><![CDATA[Defines the reason to irrevocably designate a non derivative financial instrument at fair value through profit or loss (use of fair value option). Is not applicable for nGAAP based on BAD.]]></commentInRDBMS>
<ownerDesignName>BIRD data models</ownerDesignName>
<shouldEngineer>false</shouldEngineer>
<engineerTo>
<item key="C083FD85-D1B9-E583-74F8-D21AEF72E2BC" value="false"/>
<item key="2F95CE3A-CB8C-BD28-A553-EDBE7F94003D" value="false"/>
<item key="D692C862-C9D4-A57D-98F6-C0D7D8DBCCCF" value="false"/>
<item key="5CF11FB1-F95F-60BC-DA98-ABFECEE7315A" value="false"/>
</engineerTo>
<typeID>1312D78D-A5F6-B25F-0715-6E131635D11D</typeID>
<adequatelyNormalized>NO</adequatelyNormalized>
<expectedVolumes>0</expectedVolumes>
<fwdEngineeringStrategyName>Single Table</fwdEngineeringStrategyName>
<growthPercent>0</growthPercent>
<growthType>Year</growthType>
<maxVolumes>9999999</maxVolumes>
<minVolumes>0</minVolumes>
<normalForm>Third</normalForm>
<preferredAbbreviation>FV_DSGNTN</preferredAbbreviation>
<attributes itemClass="oracle.dbtools.crest.model.design.logical.Attribute">
<Attribute name="Fair value designation" id="01496674-F366-280F-F0B0-99971AA9873A">
<createdBy>ostarij</createdBy>
<createdTime>2022-07-28 15:53:10 UTC</createdTime>
<comment><![CDATA[Defines the reason to irrevocably designate a non derivative financial instrument at fair value through profit or loss (use of fair value option). Is not applicable for nGAAP based on BAD.]]></comment>
<ownerDesignName>BIRD data models</ownerDesignName>
<engineerTo>
<item key="C083FD85-D1B9-E583-74F8-D21AEF72E2BC" value="true"/>
<item key="2F95CE3A-CB8C-BD28-A553-EDBE7F94003D" value="true"/>
<item key="D692C862-C9D4-A57D-98F6-C0D7D8DBCCCF" value="true"/>
<item key="5CF11FB1-F95F-60BC-DA98-ABFECEE7315A" value="true"/>
</engineerTo>
<use>0</use>
<logicalDatatype>A3A3C77D-0366-9768-FF89-1C25E56881C8</logicalDatatype>
<domain>810501BF-2E6A-06B1-952B-20D55D2F5983</domain>
<ownDataTypeParameters>,,</ownDataTypeParameters>
<preferredAbbreviation>FVO_DSGNTN</preferredAbbreviation>
</Attribute>
</attributes>
<identifiers itemClass="oracle.dbtools.crest.model.design.logical.CandidateKey">
<identifier id="7E7F31A7-AD07-9B25-B21C-B220DFB23A82" name="Fair value designation PK">
<createdBy>ostarij</createdBy>
<createdTime>2022-07-28 15:53:18 UTC</createdTime>
<ownerDesignName>BIRD data models</ownerDesignName>
<engineerTo>
<item key="C083FD85-D1B9-E583-74F8-D21AEF72E2BC" value="true"/>
<item key="2F95CE3A-CB8C-BD28-A553-EDBE7F94003D" value="true"/>
<item key="D692C862-C9D4-A57D-98F6-C0D7D8DBCCCF" value="true"/>
<item key="5CF11FB1-F95F-60BC-DA98-ABFECEE7315A" value="true"/>
</engineerTo>
<pk>true</pk>
<usedAttributes>
<attributeRef>01496674-F366-280F-F0B0-99971AA9873A</attributeRef>
</usedAttributes>
</identifier>
</identifiers>
</Entity>
