<?xml version = '1.0' encoding = 'UTF-8'?>
<FKIndexAssociation class="oracle.dbtools.crest.model.design.relational.FKIndexAssociation" directorySegmentName="seg_3" id="0F7C33A0-82A4-3824-6FE1-D6714674436A" containerWithKeyObject="71312C53-A4D9-8117-73EC-337C301597AC" localFKIndex="5CE14B1E-276F-F4DD-FC2B-A6C4292E9FFF" name="TRDTNL_SCRTSTN_CRDT_FCLTY_FK">
<createdBy>nuvolia</createdBy>
<createdTime>2024-03-26 15:14:59 UTC</createdTime>
<commentInRDBMS><![CDATA[is provided]]></commentInRDBMS>
<generatorID>492F4BB1-713F-DE67-9A81-46A914E14DDE</generatorID>
<ownerDesignName>BIRD data models</ownerDesignName>
<referredTableLongName>CRDT_FCLTY</referredTableLongName>
<deleteRule>NO ACTION</deleteRule>
<referredTableID>4F70F1CA-A2E5-BFF8-5BD3-455DC435F2F8</referredTableID>
<keyObject>64442673-F8EF-B195-1E6F-A033DDC7DCBB</keyObject>
<referredKeyID>64442673-F8EF-B195-1E6F-A033DDC7DCBB</referredKeyID>
<mandatory>false</mandatory>
<refColNames>CRDT_FCLTY_ID,CRDT_FCLTY_RFRNC_DT,CRDT_FCLTY_RFRTNG_AGNT_ID</refColNames>
<transferable>true</transferable>
<rely>false</rely>
<columnDependencyConstraintGenerateInDDL>true</columnDependencyConstraintGenerateInDDL>
</FKIndexAssociation>
