<?xml version = '1.0' encoding = 'UTF-8'?>
<FKIndexAssociation class="oracle.dbtools.crest.model.design.relational.FKIndexAssociation" directorySegmentName="seg_0" id="47EC2E1E-7D99-2393-A729-0F2F60EF1149" containerWithKeyObject="CCE07DBF-C9D1-0BAC-5BD1-D1C464190AB8" localFKIndex="1C4918FC-3C6C-1680-CA95-2B4F61927716" name="Asset_pool_Loan_(excluding_repurchase_agreement)_assignment_Instrument_FK">
<createdBy>nuvolia</createdBy>
<createdTime>2024-04-11 14:37:59 UTC</createdTime>
<commentInRDBMS><![CDATA[is part of]]></commentInRDBMS>
<generatorID>AE795EBF-2362-39DE-E33B-AA327BA29559</generatorID>
<ownerDesignName>BIRD data models</ownerDesignName>
<referredTableLongName>Instrument</referredTableLongName>
<deleteRule>NO ACTION</deleteRule>
<referredTableID>88628C3E-8F8F-EC9E-ECE6-6306E035C22F</referredTableID>
<keyObject>405B51F6-F9DE-6017-A05A-A90DE1A19E87</keyObject>
<referredKeyID>405B51F6-F9DE-6017-A05A-A90DE1A19E87</referredKeyID>
<mandatory>true</mandatory>
<refColNames>Instrument_identifier,Instrument_Reference_date,Instrument_Reporting_agent_identifier</refColNames>
<transferable>true</transferable>
<rely>false</rely>
<columnDependencyConstraintGenerateInDDL>true</columnDependencyConstraintGenerateInDDL>
</FKIndexAssociation>
