<?xml version = '1.0' encoding = 'UTF-8'?>
<Relation class="oracle.dbtools.crest.model.design.logical.Relation" name="Held for sale type specifies Other non-financial liability" directorySegmentName="seg_3" id="D9BFB37B-249B-8EC9-75FA-AE400A385BAB">
<createdBy>ostarij</createdBy>
<createdTime>2022-06-27 15:09:54 UTC</createdTime>
<commentInRDBMS><![CDATA[specifies]]></commentInRDBMS>
<ownerDesignName>BIRD data models</ownerDesignName>
<engineerTo>
<item key="935F9DB7-5B1F-AD7A-2885-527EF3895C21" value="true"/>
<item key="95824C8F-787A-FE7E-FC6E-EB0A6A49B2A0" value="true"/>
<item key="E191B903-6A69-BF7E-025A-59418E56E39D" value="true"/>
<item key="70BBF9EB-559F-53F6-36C6-737D16EB7BDD" value="true"/>
</engineerTo>
<sourcePk>3E0C3075-8792-4102-E82D-9DAEA6D26C0F</sourcePk>
<identifying>true</identifying>
<optionalSource>true</optionalSource>
<optionalTarget>false</optionalTarget>
<sourceCardinality>1</sourceCardinality>
<sourceEntity>B8010F03-C9C4-D0EC-E458-F061E8B3D403</sourceEntity>
<targetCardinalityString>*</targetCardinalityString>
<targetEntity>674F17E5-E381-FA0E-7EDD-2D03CB0F96B8</targetEntity>
<transferable>true</transferable>
<deleteRule>NO ACTION</deleteRule>
</Relation>
