<?xml version = '1.0' encoding = 'UTF-8'?>
<Entity class="oracle.dbtools.crest.model.design.logical.Entity" directorySegmentName="seg_6" id="2F642772-B370-F91D-EDE4-621EC12A41A2" name="Early redemptions included type">
<createdBy>ostarij</createdBy>
<createdTime>2022-07-28 15:12:13 UTC</createdTime>
<comment><![CDATA[An indicator specifying if early redemptions have been included.]]></comment>
<ownerDesignName>BIRD data models</ownerDesignName>
<shouldEngineer>false</shouldEngineer>
<engineerTo>
<item key="C083FD85-D1B9-E583-74F8-D21AEF72E2BC" value="false"/>
<item key="2F95CE3A-CB8C-BD28-A553-EDBE7F94003D" value="false"/>
<item key="D692C862-C9D4-A57D-98F6-C0D7D8DBCCCF" value="false"/>
<item key="5CF11FB1-F95F-60BC-DA98-ABFECEE7315A" value="false"/>
</engineerTo>
<typeID>1312D78D-A5F6-B25F-0715-6E131635D11D</typeID>
<adequatelyNormalized>NO</adequatelyNormalized>
<expectedVolumes>0</expectedVolumes>
<fwdEngineeringStrategyName>Single Table</fwdEngineeringStrategyName>
<growthPercent>0</growthPercent>
<growthType>Year</growthType>
<maxVolumes>9999999</maxVolumes>
<minVolumes>0</minVolumes>
<normalForm>Third</normalForm>
<preferredAbbreviation>ERLY_RDMPTN_INCLD_TBL</preferredAbbreviation>
<attributes itemClass="oracle.dbtools.crest.model.design.logical.Attribute">
<Attribute name="Early redemptions included indicator" id="0E29611F-DF1E-257D-C302-BE72DE1F10F4">
<createdBy>ostarij</createdBy>
<createdTime>2022-07-28 15:12:24 UTC</createdTime>
<comment><![CDATA[An indicator specifying if early redemptions have been included.]]></comment>
<ownerDesignName>BIRD data models</ownerDesignName>
<engineerTo>
<item key="C083FD85-D1B9-E583-74F8-D21AEF72E2BC" value="true"/>
<item key="2F95CE3A-CB8C-BD28-A553-EDBE7F94003D" value="true"/>
<item key="D692C862-C9D4-A57D-98F6-C0D7D8DBCCCF" value="true"/>
<item key="5CF11FB1-F95F-60BC-DA98-ABFECEE7315A" value="true"/>
</engineerTo>
<use>0</use>
<logicalDatatype>A3A3C77D-0366-9768-FF89-1C25E56881C8</logicalDatatype>
<domain>F93EA851-DEF5-4958-4B6D-D58EFDF4BA5F</domain>
<ownDataTypeParameters>,,</ownDataTypeParameters>
<preferredAbbreviation>ERLY_RDMPTN_INCLSN_INDCTR</preferredAbbreviation>
</Attribute>
</attributes>
<identifiers itemClass="oracle.dbtools.crest.model.design.logical.CandidateKey">
<identifier id="21A04BC1-A5FC-9593-B460-CB1EA4F35EF1" name="Early redemptions included type PK">
<createdBy>ostarij</createdBy>
<createdTime>2022-07-28 15:12:30 UTC</createdTime>
<ownerDesignName>BIRD data models</ownerDesignName>
<engineerTo>
<item key="C083FD85-D1B9-E583-74F8-D21AEF72E2BC" value="true"/>
<item key="2F95CE3A-CB8C-BD28-A553-EDBE7F94003D" value="true"/>
<item key="D692C862-C9D4-A57D-98F6-C0D7D8DBCCCF" value="true"/>
<item key="5CF11FB1-F95F-60BC-DA98-ABFECEE7315A" value="true"/>
</engineerTo>
<pk>true</pk>
<usedAttributes>
<attributeRef>0E29611F-DF1E-257D-C302-BE72DE1F10F4</attributeRef>
</usedAttributes>
</identifier>
</identifiers>
</Entity>
